yamllib/__init__.py
yamllib/config.py
yamllib/env.py
yamllib/types.py
pyyamllib-0.1.dist-info/LICENSE.txt
pyyamllib-0.1.dist-info/METADATA
pyyamllib-0.1.dist-info/WHEEL
pyyamllib-0.1.dist-info/top_level.txt
pyyamllib-0.1.dist-info/RECORD
